getschema/__init__.py
getschema/impl.py
getschema-0.2.11.dist-info/AUTHORS.md
getschema-0.2.11.dist-info/LICENSE
getschema-0.2.11.dist-info/METADATA
getschema-0.2.11.dist-info/WHEEL
getschema-0.2.11.dist-info/entry_points.txt
getschema-0.2.11.dist-info/top_level.txt
getschema-0.2.11.dist-info/RECORD
