Metadata-Version: 2.1
Name: getschema
Version: 0.2.11
Summary: Get jsonschema from sample records
Home-page: https://github.com/anelendata/getschema
Author: Daigo Tanaka, Anelen Co., LLC
License: UNKNOWN
Platform: UNKNOWN
Classifier: Development Status :: 4 - Beta
Classifier: License :: OSI Approved :: Apache Software License
Classifier: Operating System :: MacOS :: MacOS X
Classifier: Operating System :: POSIX :: Linux
Classifier: Programming Language :: Python :: 3.9
Classifier: Programming Language :: Python :: 3.10
Classifier: Programming Language :: Python :: 3.11
Classifier: Programming Language :: Python :: 3.12
License-File: LICENSE
License-File: AUTHORS.md
Requires-Dist: jsonpath-ng >=1.5.2
Requires-Dist: python-dateutil >=2.8.1
Requires-Dist: pyyaml >=5.1
Requires-Dist: setuptools >=40.3.0
Requires-Dist: simplejson ==3.*,>=3.13.2
